module/__init__.py
module/hello.py
testpypackage-0.0.3.dist-info/LICENSE.md
testpypackage-0.0.3.dist-info/METADATA
testpypackage-0.0.3.dist-info/WHEEL
testpypackage-0.0.3.dist-info/top_level.txt
testpypackage-0.0.3.dist-info/RECORD
