Metadata-Version: 2.1
Name: testpypackage
Version: 0.0.3
Summary: My package
Home-page: UNKNOWN
Author: Vishal
Author-email: vishal126sw@gmail.com
License: UNKNOWN
Keywords: python,python3
Platform: UNKNOWN
Classifier: Development Status :: 1 - Planning
Classifier: Intended Audience :: Developers
Classifier: Programming Language :: Python :: 3
Classifier: Operating System :: Unix
Classifier: Operating System :: MacOS :: MacOS X
Classifier: Operating System :: Microsoft :: Windows
License-File: LICENSE.md
